colcon_mixin/__init__.py
colcon_mixin/mixin/__init__.py
colcon_mixin/mixin/mixin_argument.py
colcon_mixin/mixin/repository.py
colcon_mixin/subverb/__init__.py
colcon_mixin/subverb/add.py
colcon_mixin/subverb/list.py
colcon_mixin/subverb/remove.py
colcon_mixin/subverb/show.py
colcon_mixin/subverb/update.py
colcon_mixin/verb/__init__.py
colcon_mixin/verb/mixin.py
colcon_mixin-0.2.3.dist-info/LICENSE
colcon_mixin-0.2.3.dist-info/METADATA
colcon_mixin-0.2.3.dist-info/WHEEL
colcon_mixin-0.2.3.dist-info/entry_points.txt
colcon_mixin-0.2.3.dist-info/top_level.txt
colcon_mixin-0.2.3.dist-info/zip-safe
colcon_mixin-0.2.3.dist-info/RECORD
